hatena2md/__init__.py
hatena2md/__main__.py
hatena2md/hatena2md.py
hatena2md-0.1.0.dist-info/LICENSE
hatena2md-0.1.0.dist-info/METADATA
hatena2md-0.1.0.dist-info/WHEEL
hatena2md-0.1.0.dist-info/entry_points.txt
hatena2md-0.1.0.dist-info/top_level.txt
hatena2md-0.1.0.dist-info/RECORD
