Metadata-Version: 2.1
Name: hatena2md
Version: 0.1.0
Summary: Python application to convert Hatena Notation (はてな記法) to Markdown
Home-page: https://github.com/schroeding/hatena2md
Author: Florian Eder
Author-email: others.meder@gmail.com
License: UNKNOWN
Platform: UNKNOWN
Classifier: Development Status :: 4 - Beta
Classifier: Programming Language :: Python :: 3
Classifier: License :: Public Domain
Classifier: Operating System :: OS Independent
Classifier: Topic :: Text Processing :: Markup
Requires-Python: >=3.6
